pytimeliner/__init__.py
pytimeliner/timeliner.py
pytimeliner-0.3.dist-info/LICENSE
pytimeliner-0.3.dist-info/METADATA
pytimeliner-0.3.dist-info/WHEEL
pytimeliner-0.3.dist-info/top_level.txt
pytimeliner-0.3.dist-info/RECORD
