Metadata-Version: 2.1
Name: pytimeliner
Version: 0.3
Summary: Create a timeline by listing events with multilingual support.
Home-page: https://github.com/nowte/PyTimeliner
Author: nowte
Author-email: developerahmet31@gmail.com
Classifier: Programming Language :: Python :: 3
Classifier: License :: OSI Approved :: MIT License
Classifier: Operating System :: OS Independent
Requires-Python: >=3.6
License-File: LICENSE
Requires-Dist: googletrans==4.0.0-rc1
